erect-0.2.dist-info/METADATA
erect-0.2.dist-info/WHEEL
erect-0.2.dist-info/entry_points.txt
erect/__init__.py
erect/__main__.py
erect/cli.py
erect/core/__init__.py
erect/core/context.py
erect/core/env.py
erect/core/file.py
erect/core/task.py
erect/diagnostic/__init__.py
erect/diagnostic/graph.py
erect/diagnostic/timeline.py
erect/env.py
erect/lib/__init__.py
erect/lib/gcc/__init__.py
erect/lib/gcc/module_mapper.py
erect/lib/jinja2.py
erect/util/__init__.py
erect/util/load.py
erect/util/subprocess.py
erect/util/version.py
erect-0.2.dist-info/RECORD
