Metadata-Version: 2.1
Name: erect
Version: 0.2
Summary: Build system
Author-Email: Vegard Storheil Eriksen <zyp@jvnv.net>
License: MIT
Requires-Python: >=3.10
Requires-Dist: click>=8.1.7
Requires-Dist: jinja2>=3.1.4
Requires-Dist: packaging>=24.1
Provides-Extra: diagnostic
Requires-Dist: bokeh>=3.6.0; extra == "diagnostic"
Requires-Dist: graphviz>=0.20.3; extra == "diagnostic"
